azure/mgmt/machinelearningcompute/__init__.py
azure/mgmt/machinelearningcompute/machine_learning_compute_management_client.py
azure/mgmt/machinelearningcompute/version.py
azure/mgmt/machinelearningcompute/models/__init__.py
azure/mgmt/machinelearningcompute/models/acs_cluster_properties.py
azure/mgmt/machinelearningcompute/models/app_insights_credentials.py
azure/mgmt/machinelearningcompute/models/app_insights_properties.py
azure/mgmt/machinelearningcompute/models/auto_scale_configuration.py
azure/mgmt/machinelearningcompute/models/available_operations.py
azure/mgmt/machinelearningcompute/models/check_system_services_updates_available_response.py
azure/mgmt/machinelearningcompute/models/container_registry_credentials.py
azure/mgmt/machinelearningcompute/models/container_registry_properties.py
azure/mgmt/machinelearningcompute/models/container_service_credentials.py
azure/mgmt/machinelearningcompute/models/error_detail.py
azure/mgmt/machinelearningcompute/models/error_response.py
azure/mgmt/machinelearningcompute/models/error_response_wrapper.py
azure/mgmt/machinelearningcompute/models/global_service_configuration.py
azure/mgmt/machinelearningcompute/models/kubernetes_cluster_properties.py
azure/mgmt/machinelearningcompute/models/machine_learning_compute_management_client_enums.py
azure/mgmt/machinelearningcompute/models/operationalization_cluster.py
azure/mgmt/machinelearningcompute/models/operationalization_cluster_credentials.py
azure/mgmt/machinelearningcompute/models/operationalization_cluster_paged.py
azure/mgmt/machinelearningcompute/models/operationalization_cluster_update_parameters.py
azure/mgmt/machinelearningcompute/models/resource.py
azure/mgmt/machinelearningcompute/models/resource_operation.py
azure/mgmt/machinelearningcompute/models/resource_operation_display.py
azure/mgmt/machinelearningcompute/models/service_auth_configuration.py
azure/mgmt/machinelearningcompute/models/service_principal_properties.py
azure_mgmt_machinelearningcompute-0.4.0.dist-info/DESCRIPTION.rst
azure_mgmt_machinelearningcompute-0.4.0.dist-info/METADATA
azure_mgmt_machinelearningcompute-0.4.0.dist-info/RECORD
azure_mgmt_machinelearningcompute-0.4.0.dist-info/WHEEL
azure_mgmt_machinelearningcompute-0.4.0.dist-info/metadata.json
azure_mgmt_machinelearningcompute-0.4.0.dist-info/top_level.txt
